detoxpy/__init__.py
detoxpy/cli.py
detoxpy/detox.py
detoxpy-0.1.4.dist-info/entry_points.txt
detoxpy-0.1.4.dist-info/LICENSE
detoxpy-0.1.4.dist-info/WHEEL
detoxpy-0.1.4.dist-info/METADATA
detoxpy-0.1.4.dist-info/RECORD
